<annotation>
	<folder>my-project-name</folder>
	<filename>IMG_5884.jpg</filename>
	<path>/my-project-name/IMG_5884.jpg</path>
	<source>
		<database>Unspecified</database>
	</source>
	<size>
		<width>6048</width>
		<height>8064</height>
		<depth>3</depth>
	</size>
	<object>
		<name>Varroa</name>
		<pose>Unspecified</pose>
		<truncated>0</truncated>
		<difficult>0</difficult>
		<bndbox>
			<xmin>975</xmin>
			<ymin>5644</ymin>
			<xmax>1041</xmax>
			<ymax>5693</ymax>
		</bndbox>
	</object>
	<object>
		<name>Varroa</name>
		<pose>Unspecified</pose>
		<truncated>0</truncated>
		<difficult>0</difficult>
		<bndbox>
			<xmin>103</xmin>
			<ymin>4165</ymin>
			<xmax>147</xmax>
			<ymax>4217</ymax>
		</bndbox>
	</object>
</annotation>